gri_resolver/__init__.py
gri_resolver/cache.py
gri_resolver/cli.py
gri_resolver/config.py
gri_resolver/downloader.py
gri_resolver/investigate.py
gri_resolver/item_scoring.py
gri_resolver/logging.py
gri_resolver/regions.py
gri_resolver/resolver.py
gri_resolver/tiles.py
gri_resolver/web_api.py
gri_resolver/integrations/__init__.py
gri_resolver/integrations/gri_finder.py
gri_resolver/integrations/stac_mgrs.py
gri_resolver/kml/S2A_OPER_GIP_TILPAR_MPC__20151209T095117_V20150622T000000_21000101T000000_B00.kml
gri_resolver/static/js/common.js
gri_resolver/static/js/downloads.js
gri_resolver/static/js/navigation.js
gri_resolver/static/js/roi.js
gri_resolver/static/js/storage.js
gri_resolver/static/js/tiles.js
gri_resolver/templates/index.html
gri_resolver/templates/partials/downloads.html
gri_resolver/templates/partials/storage.html
gri_resolver/templates/partials/tiles.html
gri_resolver-1.2.1.dist-info/licenses/LICENSE
gri_resolver-1.2.1.dist-info/METADATA
gri_resolver-1.2.1.dist-info/WHEEL
gri_resolver-1.2.1.dist-info/entry_points.txt
gri_resolver-1.2.1.dist-info/top_level.txt
gri_resolver-1.2.1.dist-info/RECORD
