Metadata-Version: 2.4
Name: gri_resolver
Version: 1.2.1
Summary: Tile-based GRI resolver, downloader, cache, and investigation tools
Author: gael
License-Expression: MIT
Project-URL: Homepage, https://example.invalid/gri_resolver
Project-URL: Repository, https://example.invalid/gri_resolver.git
Project-URL: Issues, https://example.invalid/gri_resolver/issues
Keywords: GRI,STAC,MGRS,satellite,imagery,tiles
Classifier: Programming Language :: Python :: 3
Classifier: Programming Language :: Python :: 3 :: Only
Classifier: Programming Language :: Python :: 3.9
Classifier: Programming Language :: Python :: 3.10
Classifier: Programming Language :: Python :: 3.11
Classifier: Operating System :: OS Independent
Classifier: Topic :: Scientific/Engineering :: GIS
Requires-Python: >=3.9
License-File: LICENSE
Requires-Dist: requests>=2.31.0
Requires-Dist: tqdm>=4.66.0
Requires-Dist: python-dateutil>=2.8.2
Requires-Dist: mgrs>=1.4.5
Requires-Dist: packaging>=23.2
Requires-Dist: fastapi>=0.104.0
Requires-Dist: uvicorn[standard]>=0.24.0
Requires-Dist: python-multipart>=0.0.6
Requires-Dist: jinja2>=3.1.2
Requires-Dist: pillow>=10.0.0
Requires-Dist: rasterio>=1.3.0
Dynamic: license-file
